{
  "schema_version": "0.1",
  "library_id": "kosmo-asset-demo",
  "name": "KosmoAsset Demo Library",
  "description": "Small review-only sample for reusable 2D, material and 3D asset metadata.",
  "status": "draft",
  "rights_scope": "local_review_only",
  "created_at": "2026-05-25",
  "updated_at": "2026-05-26",
  "storage_policy": {
    "uploads_allowed": false,
    "public_assets_allowed": false,
    "local_assets_allowed": true,
    "max_local_size_mb": 100,
    "notes": [
      "No R2 upload, no public download and no D1 write in this demo.",
      "Assets are review metadata until rights and export quality are checked."
    ]
  },
  "assets": [
    {
      "id": "axis-marker-svg-001",
      "title": "Kosmo Axis Marker",
      "description": "Minimal SVG annotation symbol for plan and section overlays.",
      "asset_type": "2d_symbol",
      "category": "annotation",
      "source_kind": "generated",
      "source_basis": [
        "Generated directly inside the repository as a neutral Cosmos graphic test asset."
      ],
      "rights_status": "own_work",
      "license": "internal_demo",
      "credit": "Architecture Cosmos generated asset",
      "public_use_allowed": false,
      "local_only": true,
      "review_status": "draft",
      "confidence": 0.85,
      "formats": [
        {
          "format": "svg",
          "path": "assets/svg/axis-marker.svg",
          "software": [
            "web",
            "kosmo",
            "generic"
          ],
          "status": "exists"
        },
        {
          "format": "dxf",
          "planned_r2_key": "assets/kosmo-asset-demo/axis-marker-svg-001/axis-marker.dxf",
          "software": [
            "archicad",
            "generic"
          ],
          "status": "exists",
          "path": "assets/dxf/axis-marker-svg-001.dxf"
        }
      ],
      "preview": {
        "kind": "axis_marker",
        "label": "Achse",
        "primary": "#00e7ff",
        "secondary": "#f5b342"
      },
      "export_targets": [
        "svg",
        "dxf",
        "web",
        "layout"
      ],
      "tags": [
        "axis",
        "annotation",
        "plan",
        "kosmo-style",
        "dxf",
        "cad-export"
      ],
      "material_tags": [],
      "generated_asset_profile": {
        "generated_at": "2026-05-26T13:10:26.001Z",
        "generator": "kosmo-asset-generate-demo-dxf",
        "status": "local_review_dxf_generated",
        "caveat": "Diagrammatic axis symbol only. It is not a measured project drawing or public release.",
        "entity_count": 7,
        "layer_names": [
          "KOSMO_AXIS_PRIMARY",
          "KOSMO_AXIS_SECONDARY",
          "KOSMO_TEXT"
        ]
      }
    },
    {
      "id": "warm-concrete-material-001",
      "title": "Warm Concrete Study Material",
      "description": "Neutral material metadata sample for Blender/ArchiCAD material mapping.",
      "asset_type": "material",
      "category": "material",
      "source_kind": "generated",
      "source_basis": [
        "Generated from generic material-analysis taxonomy; not derived from a protected project image."
      ],
      "rights_status": "generated_needs_review",
      "license": "review_only",
      "credit": "Architecture Cosmos generated material study",
      "public_use_allowed": false,
      "local_only": true,
      "review_status": "planned",
      "confidence": 0.62,
      "formats": [
        {
          "format": "material_json",
          "path": "assets/materials/warm-concrete.material.json",
          "software": [
            "blender",
            "archicad",
            "kosmo"
          ],
          "status": "exists"
        }
      ],
      "preview": {
        "kind": "material_swatch",
        "label": "Beton",
        "primary": "#b9aca0",
        "secondary": "#f5b342",
        "swatches": [
          "#c9beb4",
          "#b9aca0",
          "#8f8175"
        ]
      },
      "export_targets": [
        "blender",
        "archicad",
        "web"
      ],
      "tags": [
        "concrete",
        "mineral",
        "material-layer",
        "neutral"
      ],
      "material_tags": [
        "beton",
        "mineralisch"
      ]
    },
    {
      "id": "generic-column-glb-001",
      "title": "Generic Column GLB Slot",
      "description": "Local diagrammatic GLB component for Blender/ArchiCAD exchange tests.",
      "asset_type": "glb_model",
      "category": "structure",
      "source_kind": "generated",
      "source_basis": [
        "Generated inside Architecture Cosmos as a neutral analytical structural component.",
        "No protected project plan, image or third-party model was used."
      ],
      "rights_status": "generated_needs_review",
      "license": "review_only",
      "credit": "Architecture Cosmos generated asset slot",
      "public_use_allowed": false,
      "local_only": true,
      "review_status": "draft",
      "confidence": 0.58,
      "formats": [
        {
          "format": "glb",
          "planned_r2_key": "assets/kosmo-asset-demo/generic-column-glb-001/generic-column.glb",
          "software": [
            "blender",
            "web",
            "archicad"
          ],
          "status": "exists",
          "path": "assets/models/generic-column-glb-001.glb"
        }
      ],
      "preview": {
        "kind": "wireframe_component",
        "label": "Stütze",
        "primary": "#00e7ff",
        "secondary": "#ff4fd8"
      },
      "export_targets": [
        "glb",
        "blender",
        "archicad",
        "web"
      ],
      "tags": [
        "column",
        "structure",
        "glb",
        "diagrammatic",
        "asset-review"
      ],
      "material_tags": [
        "beton",
        "mineralisch"
      ],
      "dimensions": {
        "width_m": 0.35,
        "depth_m": 0.35,
        "height_m": 3,
        "scale": "1:1 diagrammatic"
      },
      "generated_asset_profile": {
        "generated_at": "2026-05-26T12:54:21.120Z",
        "generator": "kosmo-asset-generate-demo-glb",
        "status": "local_review_glb_generated",
        "caveat": "Diagrammatic study asset only. It is not a measured BIM component or public release.",
        "triangle_count": 176,
        "layer_names": [
          "structure/column_core_round",
          "structure/base_plate_reference",
          "structure/top_plate_reference",
          "analysis/axis_x",
          "analysis/axis_z"
        ]
      }
    }
  ]
}
