{
  "schema_version": "0.1",
  "generated_at": "2026-06-14T18:20:25.496Z",
  "status": "owner_unlock_pipeline_checkpoint_guard_passed",
  "policy": {
    "validates_checkpoint_only": true,
    "records_decisions": false,
    "writes_intake_file_now": false,
    "mutates_session_files_now": false,
    "reads_private_content_now": false,
    "runs_private_inventory_now": false,
    "public_ready_after_check": 0
  },
  "source_refs": [
    "data/kosmo-owner-unlock-pipeline-checkpoint-2026-06-14.json"
  ],
  "summary": {
    "checks": 21,
    "passed": 21,
    "failures": 0,
    "warnings": 0,
    "public_ready_after_check": 0
  },
  "checks": [
    {
      "id": "status_ready",
      "status": "passed",
      "evidence": "owner_unlock_pipeline_checkpoint_ready"
    },
    {
      "id": "policy_checkpoint_only",
      "status": "passed",
      "evidence": true
    },
    {
      "id": "policy_no_decisions",
      "status": "passed",
      "evidence": false
    },
    {
      "id": "policy_no_intake_write",
      "status": "passed",
      "evidence": false
    },
    {
      "id": "policy_no_session_mutation",
      "status": "passed",
      "evidence": false
    },
    {
      "id": "policy_no_commands_now",
      "status": "passed",
      "evidence": false
    },
    {
      "id": "policy_no_private_reads",
      "status": "passed",
      "evidence": false
    },
    {
      "id": "policy_no_inventory_now",
      "status": "passed",
      "evidence": false
    },
    {
      "id": "public_ready_zero",
      "status": "passed",
      "evidence": 0
    },
    {
      "id": "eleven_components",
      "status": "passed",
      "evidence": 11
    },
    {
      "id": "all_components_ready",
      "status": "passed",
      "evidence": "11/11"
    },
    {
      "id": "guard_checks_113",
      "status": "passed",
      "evidence": 113
    },
    {
      "id": "guard_checks_all_passed",
      "status": "passed",
      "evidence": "113/113"
    },
    {
      "id": "latest_handoffs_include_183_or_newer",
      "status": "passed",
      "evidence": 194
    },
    {
      "id": "owner_reply_pending",
      "status": "passed",
      "evidence": "pending"
    },
    {
      "id": "source_root_blocked",
      "status": "passed",
      "evidence": "blocked_until_explicit_owner_reply_and_guards"
    },
    {
      "id": "component_public_ready_zero",
      "status": "passed",
      "evidence": ""
    },
    {
      "id": "hard_stop_no_approval",
      "status": "passed",
      "evidence": "do not treat this checkpoint as owner approval. do not read private content from this checkpoint. do not run private inventory from this checkpoint. do not mark private-derived material public-ready."
    },
    {
      "id": "hard_stop_no_private_content",
      "status": "passed",
      "evidence": "do not treat this checkpoint as owner approval. do not read private content from this checkpoint. do not run private inventory from this checkpoint. do not mark private-derived material public-ready."
    },
    {
      "id": "hard_stop_no_inventory",
      "status": "passed",
      "evidence": "do not treat this checkpoint as owner approval. do not read private content from this checkpoint. do not run private inventory from this checkpoint. do not mark private-derived material public-ready."
    },
    {
      "id": "hard_stop_no_public_ready",
      "status": "passed",
      "evidence": "do not treat this checkpoint as owner approval. do not read private content from this checkpoint. do not run private inventory from this checkpoint. do not mark private-derived material public-ready."
    }
  ]
}
